odoo/addons/donation_stay/README.rst
odoo/addons/donation_stay/__init__.py
odoo/addons/donation_stay/__manifest__.py
odoo/addons/donation_stay/demo/demo.xml
odoo/addons/donation_stay/i18n/donation_stay.pot
odoo/addons/donation_stay/i18n/fr.po
odoo/addons/donation_stay/migrations/14.0.2.0.0/post-migration.py
odoo/addons/donation_stay/migrations/14.0.2.0.0/pre-migration.py
odoo/addons/donation_stay/models/__init__.py
odoo/addons/donation_stay/models/donation.py
odoo/addons/donation_stay/models/res_company.py
odoo/addons/donation_stay/models/stay.py
odoo/addons/donation_stay/readme/CONTRIBUTORS.rst
odoo/addons/donation_stay/readme/DESCRIPTION.rst
odoo/addons/donation_stay/readme/USAGE.rst
odoo/addons/donation_stay/security/ir.model.access.csv
odoo/addons/donation_stay/static/description/icon.png
odoo/addons/donation_stay/static/description/index.html
odoo/addons/donation_stay/tests/__init__.py
odoo/addons/donation_stay/tests/test_donate_from_stay.py
odoo/addons/donation_stay/views/donation.xml
odoo/addons/donation_stay/views/stay.xml
odoo/addons/donation_stay/wizard/__init__.py
odoo/addons/donation_stay/wizard/create_donation_stay.py
odoo/addons/donation_stay/wizard/create_donation_stay_view.xml
odoo/addons/donation_stay/wizard/res_config_settings.py
odoo/addons/donation_stay/wizard/res_config_settings.xml
odoo14_addon_donation_stay-14.0.3.0.0.dist-info/METADATA
odoo14_addon_donation_stay-14.0.3.0.0.dist-info/WHEEL
odoo14_addon_donation_stay-14.0.3.0.0.dist-info/top_level.txt
odoo14_addon_donation_stay-14.0.3.0.0.dist-info/RECORD
