Metadata-Version: 2.1
Name: odoo14-addon-donation-stay
Version: 14.0.3.0.0
Summary: Create donations from a stay
Home-page: https://github.com/OCA/vertical-abbey
Author: Barroux Abbey, Akretion, Odoo Community Association (OCA)
Author-email: support@odoo-community.org
License: AGPL-3
Platform: UNKNOWN
Classifier: Programming Language :: Python
Classifier: Framework :: Odoo
Classifier: Framework :: Odoo :: 14.0
Classifier: License :: OSI Approved :: GNU Affero General Public License v3
Requires-Python: >=3.6
Requires-Dist: odoo14-addon-donation
Requires-Dist: odoo14-addon-stay
Requires-Dist: odoo <14.1dev,>=14.0a
